ec2_metadata/__init__.py
ec2_metadata/py.typed
ec2_metadata-2.17.0.dist-info/licenses/LICENSE
ec2_metadata-2.17.0.dist-info/METADATA
ec2_metadata-2.17.0.dist-info/WHEEL
ec2_metadata-2.17.0.dist-info/top_level.txt
ec2_metadata-2.17.0.dist-info/RECORD
